MANIFEST.in
README.md
setup.py
cl1/.version.py
cl1/__init__.py
cl1.egg-info/PKG-INFO
cl1.egg-info/SOURCES.txt
cl1.egg-info/dependency_links.txt
cl1.egg-info/not-zip-safe
cl1.egg-info/requires.txt
cl1.egg-info/top_level.txt
cl1/classes/__init__.py
cl1/classes/cl1/__init__.py
cl1/classes/config/__init__.py
cl1/classes/exceptions/__init__.py
cl1/classes/utils/__init__.py