Metadata-Version: 1.0
Name: cl1
Version: 1.11.9
Summary: Some description.
Home-page: http://github.com/vandenberghinc/cl1
Author: Daan van den Bergh
Author-email: vandenberghinc.contact@gmail.com
License: MIT
Platform: UNKNOWN
